Workbook

Sheet 价格数据
A1: Date | B1: STOCK_Close | C1: GOLD_Close | D1: BOND_Close | E1: CASH_Close
A2: 20130729 | B2: 2.221 | C2: 2.626 | D2: 99.08 | E2: 100.005
A3: 20130730 | B3: 2.234 | C3: 2.646 | D3: 99.195 | E3: 100.004
A4: 20130731 | B4: 2.239 | C4: 2.657 | D4: 99.382 | E4: 100.005
A5: 20130801 | B5: 2.298 | C5: 2.643 | D5: 99.481 | E5: 100.014
A6: 20130802 | B6: 2.294 | C6: 2.578 | D6: 99.28 | E6: 100.048
A7: 20130803 | B7: 2.294 | C7: 2.578 | D7: 99.28 | E7: 100.048
A8: 20130804 | B8: 2.294 | C8: 2.578 | D8: 99.28 | E8: 100.048
A9: 20130805 | B9: 2.327 | C9: 2.63 | D9: 99.28 | E9: 100.02
A10: 20130806 | B10: 2.342 | C10: 2.591 | D10: 99.29 | E10: 100.009
A11: 20130807 | B11: 2.326 | C11: 2.574 | D11: 98.946 | E11: 100.007
A12: 20130808 | B12: 2.327 | C12: 2.586 | D12: 98.79 | E12: 100.006
A13: 20130809 | B13: 2.337 | C13: 2.616 | D13: 98.761 | E13: 100.02
... A4518: 20251209 | B4518: 4.708 | C4518: 9.046 | D4518: 140.545 | E4518: 100

Sheet 参数设置
A1: 参数 | B1: 值
A2: 初始资金 | B2: 100000
A3: 调仓阈值K | B3: 0.02
A4: 初始权重 | B4: 0.25
A5: 手续费率 | B5: 0.0005

Sheet 回测
A1: Date | B1: STOCK_Value | C1: GOLD_Value | D1: BOND_Value | E1: CASH_Value | F1: Total | G1: STOCK_W | H1: GOLD_W | I1: BOND_W | J1: CASH_W | K1: 是否调仓 | L1: 目标_STOCK | M1: 目标_GOLD | N1: 目标_BOND | O1: 目标_CASH | P1: 成交额_STOCK | Q1: 成交额_GOLD | R1: 成交额_BOND | S1: 成交额_CASH | T1: 成交额总和 | U1: 手续费
A2: 41484 | B2: =VALUE(参数设置!B2) -> 100000 | C2: =VALUE(参数设置!C2)*VALUE(参数设置!C3) -> 0 | D2: =VALUE(参数设置!D2)*VALUE(参数设置!D3) -> 0 | E2: =VALUE(参数设置!E2)*VALUE(参数设置!E3) -> 0 | F2: =SUM(B2:E2) -> 100000 | G2: =IFERROR(B2/F2,0) -> 1 | H2: =IFERROR(C2/G2,0) -> 0 | I2: =IFERROR(D2/H2,0) -> 0 | J2: =IFERROR(E2/I2,0) -> 0 | K2: 是
A3: 41485 | B3: =IF(K2="是",F2*0.25*(价格数据!B3/价格数据!B2),B2*(价格数据!B3/价格数据!B2)) -> 25146.33 | C3: =IF(K2="是",F2*0.25*(价格数据!C3/价格数据!C2),C2*(价格数据!C3/价格数据!C2)) -> 25190.404 | D3: =IF(K2="是",F2*0.25*(价格数据!D3/价格数据!D2),D2*(价格数据!D3/价格数据!D2)) -> 25029.017 | E3: =IF(K2="是",F2*0.25*(价格数据!E3/价格数据!E2),E2*(价格数据!E3/价格数据!E2)) -> 24999.75 | F3: =B3+C3+D3+E3 -> 100365.5 | G3: =B3/F3 -> 0.25054755 | H3: =C3/F3 -> 0.25098668 | I3: =D3/F3 -> 0.24937869 | J3: =E3/F3 -> 0.24908708 | K3: =IF(OR( ROUND(G3,4)>(0.25+参数设置!B$3), ROUND(G3,4)<(0.25-参数设置!B$3), ROUND(H3,4)>(0.25+参数设置!B$3), ROUND(H3,4)<(0.25-参数设置!B$3), ROUND(I3,4)>(0.25+参数设置!B$3), ROUND(I3,4)<(0.25-参数设置!B$3), ROUND(J3,4)>(0.25+参数设置!B$3), ROUND(J3,4)<(0.25-参数设置!B$3) ),"是","否") -> 否 | L3: =IF(K3="是",F3*0.25,B3) -> 25146.33 | M3: =IF(K3="是",F3*0.25,C3) -> 25190.404 | N3: =IF(K3="是",F3*0.25,D3) -> 25029.017 | O3: =IF(K3="是",F3*0.25,E3) -> 24999.75 | P3: =IF(K3="是",ABS(L3-B3),0) -> 0 | Q3: =IF(K3="是",ABS(M3-C3),0) -> 0 | R3: =IF(K3="是",ABS(N3-D3),0) -> 0 | S3: =IF(K3="是",ABS(O3-E3),0) -> 0 | T3: =P3+Q3+R3+S3 -> 0 | U3: =T3*参数设置!B4 -> 0
A4: 41486 | B4: =IF(K3="是",F3*0.25*(价格数据!B4/价格数据!B3),B3*(价格数据!B4/价格数据!B3)) -> 25202.611 | C4: =IF(K3="是",F3*0.25*(价格数据!C4/价格数据!C3),C3*(价格数据!C4/价格数据!C3)) -> 25295.126 | D4: =IF(K3="是",F3*0.25*(价格数据!D4/价格数据!D3),D3*(价格数据!D4/价格数据!D3)) -> 25076.201 | E4: =IF(K3="是",F3*0.25*(价格数据!E4/价格数据!E3),E3*(价格数据!E4/价格数据!E3)) -> 25000 | F4: =B4+C4+D4+E4 -> 100573.94 | G4: =B4/F4 -> 0.25058789 | H4: =C4/F4 -> 0.25150776 | I4: =D4/F4 -> 0.249331 | J4: =E4/F4 -> 0.24857334 | K4: =IF(OR( ROUND(G4,4)>(0.25+参数设置!B$3), ROUND(G4,4)<(0.25-参数设置!B$3), ROUND(H4,4)>(0.25+参数设置!B$3), ROUND(H4,4)<(0.25-参数设置!B$3), ROUND(I4,4)>(0.25+参数设置!B$3), ROUND(I4,4)<(0.25-参数设置!B$3), ROUND(J4,4)>(0.25+参数设置!B$3), ROUND(J4,4)<(0.25-参数设置!B$3) ),"是","否") -> 否 | L4: =IF(K4="是",F4*0.25,B4) -> 25202.611 | M4: =IF(K4="是",F4*0.25,C4) -> 25295.126 | N4: =IF(K4="是",F4*0.25,D4) -> 25076.201 | O4: =IF(K4="是",F4*0.25,E4) -> 25000 | P4: =IF(K4="是",ABS(L4-B4),0) -> 0 | Q4: =IF(K4="是",ABS(M4-C4),0) -> 0 | R4: =IF(K4="是",ABS(N4-D4),0) -> 0 | S4: =IF(K4="是",ABS(O4-E4),0) -> 0 | T4: =P4+Q4+R4+S4 -> 0 | U4: =T4*参数设置!B5 -> 0
A5: 41487 | B5: =IF(K4="是",F4*0.25*(价格数据!B5/价格数据!B4),B4*(价格数据!B5/价格数据!B4)) -> 25866.727 | C5: =IF(K4="是",F4*0.25*(价格数据!C5/价格数据!C4),C4*(价格数据!C5/价格数据!C4)) -> 25161.843 | D5: =IF(K4="是",F4*0.25*(价格数据!D5/价格数据!D4),D4*(价格数据!D5/价格数据!D4)) -> 25101.181 | E5: =IF(K4="是",F4*0.25*(价格数据!E5/价格数据!E4),E4*(价格数据!E5/价格数据!E4)) -> 25002.25 | F5: =B5+C5+D5+E5 -> 101132 | G5: =B5/F5 -> 0.25577193 | H5: =C5/F5 -> 0.24880199 | I5: =D5/F5 -> 0.24820216 | J5: =E5/F5 -> 0.24722392 | K5: =IF(OR( ROUND(G5,4)>(0.25+参数设置!B$3), ROUND(G5,4)<(0.25-参数设置!B$3), ROUND(H5,4)>(0.25+参数设置!B$3), ROUND(H5,4)<(0.25-参数设置!B$3), ROUND(I5,4)>(0.25+参数设置!B$3), ROUND(I5,4)<(0.25-参数设置!B$3), ROUND(J5,4)>(0.25+参数设置!B$3), ROUND(J5,4)<(0.25-参数设置!B$3) ),"是","否") -> 否 | L5: =IF(K5="是",F5*0.25,B5) -> 25866.727 | M5: =IF(K5="是",F5*0.25,C5) -> 25161.843 | N5: =IF(K5="是",F5*0.25,D5) -> 25101.181 | O5: =IF(K5="是",F5*0.25,E5) -> 25002.25 | P5: =IF(K5="是",ABS(L5-B5),0) -> 0 | Q5: =IF(K5="是",ABS(M5-C5),0) -> 0 | R5: =IF(K5="是",ABS(N5-D5),0) -> 0 | S5: =IF(K5="是",ABS(O5-E5),0) -> 0 | T5: =P5+Q5+R5+S5 -> 0 | U5: =T5*参数设置!B6 -> 0
A6: 41488 | B6: =IF(K5="是",F5*0.25*(价格数据!B6/价格数据!B5),B5*(价格数据!B6/价格数据!B5)) -> 25821.702 | C6: =IF(K5="是",F5*0.25*(价格数据!C6/价格数据!C5),C5*(价格数据!C6/价格数据!C5)) -> 24543.031 | D6: =IF(K5="是",F5*0.25*(价格数据!D6/价格数据!D5),D5*(价格数据!D6/价格数据!D5)) -> 25050.464 | E6: =IF(K5="是",F5*0.25*(价格数据!E6/价格数据!E5),E5*(价格数据!E6/价格数据!E5)) -> 25010.749 | F6: =B6+C6+D6+E6 -> 100425.95 | G6: =B6/F6 -> 0.25712182 | H6: =C6/F6 -> 0.24438934 | I6: =D6/F6 -> 0.24944215 | J6: =E6/F6 -> 0.24904669 | K6: =IF(OR( ROUND(G6,4)>(0.25+参数设置!B$3), ROUND(G6,4)<(0.25-参数设置!B$3), ROUND(H6,4)>(0.25+参数设置!B$3), ROUND(H6,4)<(0.25-参数设置!B$3), ROUND(I6,4)>(0.25+参数设置!B$3), ROUND(I6,4)<(0.25-参数设置!B$3), ROUND(J6,4)>(0.25+参数设置!B$3), ROUND(J6,4)<(0.25-参数设置!B$3) ),"是","否") -> 否 | L6: =IF(K6="是",F6*0.25,B6) -> 25821.702 | M6: =IF(K6="是",F6*0.25,C6) -> 24543.031 | N6: =IF(K6="是",F6*0.25,D6) -> 25050.464 | O6: =IF(K6="是",F6*0.25,E6) -> 25010.749 | P6: =IF(K6="是",ABS(L6-B6),0) -> 0 | Q6: =IF(K6="是",ABS(M6-C6),0) -> 0 | R6: =IF(K6="是",ABS(N6-D6),0) -> 0 | S6: =IF(K6="是",ABS(O6-E6),0) -> 0 | T6: =P6+Q6+R6+S6 -> 0 | U6: =T6*参数设置!B7 -> 0
A7: 41489 | B7: =IF(K6="是",F6*0.25*(价格数据!B7/价格数据!B6),B6*(价格数据!B7/价格数据!B6)) -> 25821.702 | C7: =IF(K6="是",F6*0.25*(价格数据!C7/价格数据!C6),C6*(价格数据!C7/价格数据!C6)) -> 24543.031 | D7: =IF(K6="是",F6*0.25*(价格数据!D7/价格数据!D6),D6*(价格数据!D7/价格数据!D6)) -> 25050.464 | E7: =IF(K6="是",F6*0.25*(价格数据!E7/价格数据!E6),E6*(价格数据!E7/价格数据!E6)) -> 25010.749 | F7: =B7+C7+D7+E7 -> 100425.95 | G7: =B7/F7 -> 0.25712182 | H7: =C7/F7 -> 0.24438934 | I7: =D7/F7 -> 0.24944215 | J7: =E7/F7 -> 0.24904669 | K7: =IF(OR( ROUND(G7,4)>(0.25+参数设置!B$3), ROUND(G7,4)<(0.25-参数设置!B$3), ROUND(H7,4)>(0.25+参数设置!B$3), ROUND(H7,4)<(0.25-参数设置!B$3), ROUND(I7,4)>(0.25+参数设置!B$3), ROUND(I7,4)<(0.25-参数设置!B$3), ROUND(J7,4)>(0.25+参数设置!B$3), ROUND(J7,4)<(0.25-参数设置!B$3) ),"是","否") -> 否 | L7: =IF(K7="是",F7*0.25,B7) -> 25821.702 | M7: =IF(K7="是",F7*0.25,C7) -> 24543.031 | N7: =IF(K7="是",F7*0.25,D7) -> 25050.464 | O7: =IF(K7="是",F7*0.25,E7) -> 25010.749 | P7: =IF(K7="是",ABS(L7-B7),0) -> 0 | Q7: =IF(K7="是",ABS(M7-C7),0) -> 0 | R7: =IF(K7="是",ABS(N7-D7),0) -> 0 | S7: =IF(K7="是",ABS(O7-E7),0) -> 0 | T7: =P7+Q7+R7+S7 -> 0 | U7: =T7*参数设置!B8 -> 0
A8: 41490 | B8: =IF(K7="是",F7*0.25*(价格数据!B8/价格数据!B7),B7*(价格数据!B8/价格数据!B7)) -> 25821.702 | C8: =IF(K7="是",F7*0.25*(价格数据!C8/价格数据!C7),C7*(价格数据!C8/价格数据!C7)) -> 24543.031 | D8: =IF(K7="是",F7*0.25*(价格数据!D8/价格数据!D7),D7*(价格数据!D8/价格数据!D7)) -> 25050.464 | E8: =IF(K7="是",F7*0.25*(价格数据!E8/价格数据!E7),E7*(价格数据!E8/价格数据!E7)) -> 25010.749 | F8: =B8+C8+D8+E8 -> 100425.95 | G8: =B8/F8 -> 0.25712182 | H8: =C8/F8 -> 0.24438934 | I8: =D8/F8 -> 0.24944215 | J8: =E8/F8 -> 0.24904669 | K8: =IF(OR( ROUND(G8,4)>(0.25+参数设置!B$3), ROUND(G8,4)<(0.25-参数设置!B$3), ROUND(H8,4)>(0.25+参数设置!B$3), ROUND(H8,4)<(0.25-参数设置!B$3), ROUND(I8,4)>(0.25+参数设置!B$3), ROUND(I8,4)<(0.25-参数设置!B$3), ROUND(J8,4)>(0.25+参数设置!B$3), ROUND(J8,4)<(0.25-参数设置!B$3) ),"是","否") -> 否 | L8: =IF(K8="是",F8*0.25,B8) -> 25821.702 | M8: =IF(K8="是",F8*0.25,C8) -> 24543.031 | N8: =IF(K8="是",F8*0.25,D8) -> 25050.464 | O8: =IF(K8="是",F8*0.25,E8) -> 25010.749 | P8: =IF(K8="是",ABS(L8-B8),0) -> 0 | Q8: =IF(K8="是",ABS(M8-C8),0) -> 0 | R8: =IF(K8="是",ABS(N8-D8),0) -> 0 | S8: =IF(K8="是",ABS(O8-E8),0) -> 0 | T8: =P8+Q8+R8+S8 -> 0 | U8: =T8*参数设置!B9 -> 0
A9: 41491 | B9: =IF(K8="是",F8*0.25*(价格数据!B9/价格数据!B8),B8*(价格数据!B9/价格数据!B8)) -> 26193.156 | C9: =IF(K8="是",F8*0.25*(价格数据!C9/价格数据!C8),C8*(价格数据!C9/价格数据!C8)) -> 25038.081 | D9: =IF(K8="是",F8*0.25*(价格数据!D9/价格数据!D8),D8*(价格数据!D9/价格数据!D8)) -> 25050.464 | E9: =IF(K8="是",F8*0.25*(价格数据!E9/价格数据!E8),E8*(价格数据!E9/价格数据!E8)) -> 25003.75 | F9: =B9+C9+D9+E9 -> 101285.45 | G9: =B9/F9 -> 0.25860729 | H9: =C9/F9 -> 0.24720313 | I9: =D9/F9 -> 0.2473254 | J9: =E9/F9 -> 0.24686418 | K9: =IF(OR( ROUND(G9,4)>(0.25+参数设置!B$3), ROUND(G9,4)<(0.25-参数设置!B$3), ROUND(H9,4)>(0.25+参数设置!B$3), ROUND(H9,4)<(0.25-参数设置!B$3), ROUND(I9,4)>(0.25+参数设置!B$3), ROUND(I9,4)<(0.25-参数设置!B$3), ROUND(J9,4)>(0.25+参数设置!B$3), ROUND(J9,4)<(0.25-参数设置!B$3) ),"是","否") -> 否 | L9: =IF(K9="是",F9*0.25,B9) -> 26193.156 | M9: =IF(K9="是",F9*0.25,C9) -> 25038.081 | N9: =IF(K9="是",F9*0.25,D9) -> 25050.464 | O9: =IF(K9="是",F9*0.25,E9) -> 25003.75 | P9: =IF(K9="是",ABS(L9-B9),0) -> 0 | Q9: =IF(K9="是",ABS(M9-C9),0) -> 0 | R9: =IF(K9="是",ABS(N9-D9),0) -> 0 | S9: =IF(K9="是",ABS(O9-E9),0) -> 0 | T9: =P9+Q9+R9+S9 -> 0 | U9: =T9*参数设置!B10 -> 0
A10: 41492 | B10: =IF(K9="是",F9*0.25*(价格数据!B10/价格数据!B9),B9*(价格数据!B10/价格数据!B9)) -> 26361.999 | C10: =IF(K9="是",F9*0.25*(价格数据!C10/价格数据!C9),C9*(价格数据!C10/价格数据!C9)) -> 24666.794 | D10: =IF(K9="是",F9*0.25*(价格数据!D10/价格数据!D9),D9*(价格数据!D10/价格数据!D9)) -> 25052.987 | E10: =IF(K9="是",F9*0.25*(价格数据!E10/价格数据!E9),E9*(价格数据!E10/价格数据!E9)) -> 25001 | F10: =B10+C10+D10+E10 -> 101082.78 | G10: =B10/F10 -> 0.26079614 | H10: =C10/F10 -> 0.24402567 | I10: =D10/F10 -> 0.24784624 | J10: =E10/F10 -> 0.24733194 | K10: =IF(OR( ROUND(G10,4)>(0.25+参数设置!B$3), ROUND(G10,4)<(0.25-参数设置!B$3), ROUND(H10,4)>(0.25+参数设置!B$3), ROUND(H10,4)<(0.25-参数设置!B$3), ROUND(I10,4)>(0.25+参数设置!B$3), ROUND(I10,4)<(0.25-参数设置!B$3), ROUND(J10,4)>(0.25+参数设置!B$3), ROUND(J10,4)<(0.25-参数设置!B$3) ),"是","否") -> 否 | L10: =IF(K10="是",F10*0.25,B10) -> 26361.999 | M10: =IF(K10="是",F10*0.25,C10) -> 24666.794 | N10: =IF(K10="是",F10*0.25,D10) -> 25052.987 | O10: =IF(K10="是",F10*0.25,E10) -> 25001 | P10: =IF(K10="是",ABS(L10-B10),0) -> 0 | Q10: =IF(K10="是",ABS(M10-C10),0) -> 0 | R10: =IF(K10="是",ABS(N10-D10),0) -> 0 | S10: =IF(K10="是",ABS(O10-E10),0) -> 0 | T10: =P10+Q10+R10+S10 -> 0 | U10: =T10*参数设置!B11 -> 0
A11: 41493 | B11: =IF(K10="是",F10*0.25*(价格数据!B11/价格数据!B10),B10*(价格数据!B11/价格数据!B10)) -> 26181.9 | C11: =IF(K10="是",F10*0.25*(价格数据!C11/价格数据!C10),C10*(价格数据!C11/价格数据!C10)) -> 24504.95 | D11: =IF(K10="是",F10*0.25*(价格数据!D11/价格数据!D10),D10*(价格数据!D11/价格数据!D10)) -> 24966.189 | E11: =IF(K10="是",F10*0.25*(价格数据!E11/价格数据!E10),E10*(价格数据!E11/价格数据!E10)) -> 25000.5 | F11: =B11+C11+D11+E11 -> 100653.54 | G11: =B11/F11 -> 0.26011902 | H11: =C11/F11 -> 0.24345841 | I11: =D11/F11 -> 0.24804084 | J11: =E11/F11 -> 0.24838173 | K11: =IF(OR( ROUND(G11,4)>(0.25+参数设置!B$3), ROUND(G11,4)<(0.25-参数设置!B$3), ROUND(H11,4)>(0.25+参数设置!B$3), ROUND(H11,4)<(0.25-参数设置!B$3), ROUND(I11,4)>(0.25+参数设置!B$3), ROUND(I11,4)<(0.25-参数设置!B$3), ROUND(J11,4)>(0.25+参数设置!B$3), ROUND(J11,4)<(0.25-参数设置!B$3) ),"是","否") -> 否 | L11: =IF(K11="是",F11*0.25,B11) -> 26181.9 | M11: =IF(K11="是",F11*0.25,C11) -> 24504.95 | N11: =IF(K11="是",F11*0.25,D11) -> 24966.189 | O11: =IF(K11="是",F11*0.25,E11) -> 25000.5 | P11: =IF(K11="是",ABS(L11-B11),0) -> 0 | Q11: =IF(K11="是",ABS(M11-C11),0) -> 0 | R11: =IF(K11="是",ABS(N11-D11),0) -> 0 | S11: =IF(K11="是",ABS(O11-E11),0) -> 0 | T11: =P11+Q11+R11+S11 -> 0 | U11: =T11*参数设置!B12 -> 0
A12: 41494 | B12: =IF(K11="是",F11*0.25*(价格数据!B12/价格数据!B11),B11*(价格数据!B12/价格数据!B11)) -> 26193.156 | C12: =IF(K11="是",F11*0.25*(价格数据!C12/价格数据!C11),C11*(价格数据!C12/价格数据!C11)) -> 24619.193 | D12: =IF(K11="是",F11*0.25*(价格数据!D12/价格数据!D11),D11*(价格数据!D12/价格数据!D11)) -> 24926.827 | E12: =IF(K11="是",F11*0.25*(价格数据!E12/价格数据!E11),E11*(价格数据!E12/价格数据!E11)) -> 25000.25 | F12: =B12+C12+D12+E12 -> 100739.43 | G12: =B12/F12 -> 0.26000899 | H12: =C12/F12 -> 0.24438488 | I12: =D12/F12 -> 0.24743864 | J12: =E12/F12 -> 0.24816749 | K12: =IF(OR( ROUND(G12,4)>(0.25+参数设置!B$3), ROUND(G12,4)<(0.25-参数设置!B$3), ROUND(H12,4)>(0.25+参数设置!B$3), ROUND(H12,4)<(0.25-参数设置!B$3), ROUND(I12,4)>(0.25+参数设置!B$3), ROUND(I12,4)<(0.25-参数设置!B$3), ROUND(J12,4)>(0.25+参数设置!B$3), ROUND(J12,4)<(0.25-参数设置!B$3) ),"是","否") -> 否 | L12: =IF(K12="是",F12*0.25,B12) -> 26193.156 | M12: =IF(K12="是",F12*0.25,C12) -> 24619.193 | N12: =IF(K12="是",F12*0.25,D12) -> 24926.827 | O12: =IF(K12="是",F12*0.25,E12) -> 25000.25 | P12: =IF(K12="是",ABS(L12-B12),0) -> 0 | Q12: =IF(K12="是",ABS(M12-C12),0) -> 0 | R12: =IF(K12="是",ABS(N12-D12),0) -> 0 | S12: =IF(K12="是",ABS(O12-E12),0) -> 0 | T12: =P12+Q12+R12+S12 -> 0 | U12: =T12*参数设置!B13 -> 0
A13: 41495 | B13: =IF(K12="是",F12*0.25*(价格数据!B13/价格数据!B12),B12*(价格数据!B13/价格数据!B12)) -> 26305.718 | C13: =IF(K12="是",F12*0.25*(价格数据!C13/价格数据!C12),C12*(价格数据!C13/价格数据!C12)) -> 24904.798 | D13: =IF(K12="是",F12*0.25*(价格数据!D13/价格数据!D12),D12*(价格数据!D13/价格数据!D12)) -> 24919.509 | E13: =IF(K12="是",F12*0.25*(价格数据!E13/价格数据!E12),E12*(价格数据!E13/价格数据!E12)) -> 25003.75 | F13: =B13+C13+D13+E13 -> 101133.78 | G13: =B13/F13 -> 0.26010814 | H13: =C13/F13 -> 0.24625599 | I13: =D13/F13 -> 0.24640146 | J13: =E13/F13 -> 0.24723441 | K13: =IF(OR( ROUND(G13,4)>(0.25+参数设置!B$3), ROUND(G13,4)<(0.25-参数设置!B$3), ROUND(H13,4)>(0.25+参数设置!B$3), ROUND(H13,4)<(0.25-参数设置!B$3), ROUND(I13,4)>(0.25+参数设置!B$3), ROUND(I13,4)<(0.25-参数设置!B$3), ROUND(J13,4)>(0.25+参数设置!B$3), ROUND(J13,4)<(0.25-参数设置!B$3) ),"是","否") -> 否 | L13: =IF(K13="是",F13*0.25,B13) -> 26305.718 | M13: =IF(K13="是",F13*0.25,C13) -> 24904.798 | N13: =IF(K13="是",F13*0.25,D13) -> 24919.509 | O13: =IF(K13="是",F13*0.25,E13) -> 25003.75 | P13: =IF(K13="是",ABS(L13-B13),0) -> 0 | Q13: =IF(K13="是",ABS(M13-C13),0) -> 0 | R13: =IF(K13="是",ABS(N13-D13),0) -> 0 | S13: =IF(K13="是",ABS(O13-E13),0) -> 0 | T13: =P13+Q13+R13+S13 -> 0 | U13: =T13*参数设置!B14 -> 0
A14: 41496 | B14: =IF(K13="是",F13*0.25*(价格数据!B14/价格数据!B13),B13*(价格数据!B14/价格数据!B13)) -> 26305.718 | C14: =IF(K13="是",F13*0.25*(价格数据!C14/价格数据!C13),C13*(价格数据!C14/价格数据!C13)) -> 24904.798 | D14: =IF(K13="是",F13*0.25*(价格数据!D14/价格数据!D13),D13*(价格数据!D14/价格数据!D13)) -> 24919.509 | E14: =IF(K13="是",F13*0.25*(价格数据!E14/价格数据!E13),E13*(价格数据!E14/价格数据!E13)) -> 25003.75 | F14: =B14+C14+D14+E14 -> 101133.78 | G14: =B14/F14 -> 0.26010814 | H14: =C14/F14 -> 0.24625599 | I14: =D14/F14 -> 0.24640146 | J14: =E14/F14 -> 0.24723441 | K14: =IF(OR( ROUND(G14,4)>(0.25+参数设置!B$3), ROUND(G14,4)<(0.25-参数设置!B$3), ROUND(H14,4)>(0.25+参数设置!B$3), ROUND(H14,4)<(0.25-参数设置!B$3), ROUND(I14,4)>(0.25+参数设置!B$3), ROUND(I14,4)<(0.25-参数设置!B$3), ROUND(J14,4)>(0.25+参数设置!B$3), ROUND(J14,4)<(0.25-参数设置!B$3) ),"是","否") -> 否 | L14: =IF(K14="是",F14*0.25,B14) -> 26305.718 | M14: =IF(K14="是",F14*0.25,C14) -> 24904.798 | N14: =IF(K14="是",F14*0.25,D14) -> 24919.509 | O14: =IF(K14="是",F14*0.25,E14) -> 25003.75 | P14: =IF(K14="是",ABS(L14-B14),0) -> 0 | Q14: =IF(K14="是",ABS(M14-C14),0) -> 0 | R14: =IF(K14="是",ABS(N14-D14),0) -> 0 | S14: =IF(K14="是",ABS(O14-E14),0) -> 0 | T14: =P14+Q14+R14+S14 -> 0 | U14: =T14*参数设置!B15 -> 0
... A4518: 46000 | B4518: =IF(K4517="是",F4517*0.25*(价格数据!B4518/价格数据!B4517),B4517*(价格数据!B4518/价格数据!B4517)) -> 48948.577 | C4518: =IF(K4517="是",F4517*0.25*(价格数据!C4518/价格数据!C4517),C4517*(价格数据!C4518/价格数据!C4517)) -> 48032.397 | D4518: =IF(K4517="是",F4517*0.25*(价格数据!D4518/价格数据!D4517),D4517*(价格数据!D4518/价格数据!D4517)) -> 49223.479 | E4518: =IF(K4517="是",F4517*0.25*(价格数据!E4518/价格数据!E4517),E4517*(价格数据!E4518/价格数据!E4517)) -> 49081.773 | F4518: =B4518+C4518+D4518+E4518 -> 195286.23 | G4518: =B4518/F4518 -> 0.25065043 | H4518: =C4518/F4518 -> 0.24595896 | I4518: =D4518/F4518 -> 0.25205812 | J4518: =E4518/F4518 -> 0.25133249 | K4518: =IF(OR( ROUND(G4518,4)>(0.25+参数设置!B$3), ROUND(G4518,4)<(0.25-参数设置!B$3), ROUND(H4518,4)>(0.25+参数设置!B$3), ROUND(H4518,4)<(0.25-参数设置!B$3), ROUND(I4518,4)>(0.25+参数设置!B$3), ROUND(I4518,4)<(0.25-参数设置!B$3), ROUND(J4518,4)>(0.25+参数设置!B$3), ROUND(J4518,4)<(0.25-参数设置!B$3) ),"是","否") -> 否 | L4518: =IF(K4518="是",F4518*0.25,B4518) -> 48948.577 | M4518: =IF(K4518="是",F4518*0.25,C4518) -> 48032.397 | N4518: =IF(K4518="是",F4518*0.25,D4518) -> 49223.479 | O4518: =IF(K4518="是",F4518*0.25,E4518) -> 49081.773 | P4518: =IF(K4518="是",ABS(L4518-B4518),0) -> 0 | Q4518: =IF(K4518="是",ABS(M4518-C4518),0) -> 0 | R4518: =IF(K4518="是",ABS(N4518-D4518),0) -> 0 | S4518: =IF(K4518="是",ABS(O4518-E4518),0) -> 0 | T4518: =P4518+Q4518+R4518+S4518 -> 0 | U4518: =T4518*参数设置!B4519 -> 0

Sheet 绘图
A1: Date | B1: 账户权益（左轴） | C1: 是否调仓 | D1: 调仓次数 | E1: 夏普比率 | F1: Daily_Return | G1: 历史峰值 | H1: 当期回撤（右轴） | I1: 最大回撤 | J1: 总收益/最大回撤
A2: =回测!A2 -> 41484 | B2: =回测!F2 -> 100000 | C2: =回测!K2 -> 是 | D2: =COUNTIF($C$2:C2,"是") -> 1 | E2: =IF(COUNTA(F$2:F2)<2,0,AVERAGE(F$2:F2)/_xlfn.STDEV.P(F$2:F2)*SQRT(252)) -> 0 | G2: =MAX($B$2:$B2) -> 100000 | H2: =1-($B2/$G2) -> 0 | I2: 0 | J2: =B4518/B2/I4518 -> 15.311482
A3: =回测!A3 -> 41485 | B3: =回测!F3 -> 100365.5 | C3: =回测!K3 -> 否 | D3: =COUNTIF($C$2:C3,"是") -> 1 | E3: =IF(COUNTA(F$2:F3)<2,0,AVERAGE(F$2:F3)/_xlfn.STDEV.P(F$2:F3)*SQRT(252)) -> 0 | F3: =IF(B2=0,0,B3/B2-1) -> 0.0036550111 | G3: =MAX($B$2:$B3) -> 100365.5 | H3: =1-($B3/$G3) -> 0 | I3: =MAX($I2,$H3) -> 0
A4: =回测!A4 -> 41486 | B4: =回测!F4 -> 100573.94 | C4: =回测!K4 -> 否 | D4: =COUNTIF($C$2:C4,"是") -> 1 | E4: =IF(COUNTA(F$2:F4)<2,0,AVERAGE(F$2:F4)/_xlfn.STDEV.P(F$2:F4)*SQRT(252)) -> 57.652742 | F4: =IF(B3=0,0,B4/B3-1) -> 0.0020767798 | G4: =MAX($B$2:$B4) -> 100573.94 | H4: =1-($B4/$G4) -> 0 | I4: =MAX($I3,$H4) -> 0
A5: =回测!A5 -> 41487 | B5: =回测!F5 -> 101132 | C5: =回测!K5 -> 否 | D5: =COUNTIF($C$2:C5,"是") -> 1 | E5: =IF(COUNTA(F$2:F5)<2,0,AVERAGE(F$2:F5)/_xlfn.STDEV.P(F$2:F5)*SQRT(252)) -> 42.054183 | F5: =IF(B4=0,0,B5/B4-1) -> 0.0055487775 | G5: =MAX($B$2:$B5) -> 101132 | H5: =1-($B5/$G5) -> 0 | I5: =MAX($I4,$H5) -> 0
A6: =回测!A6 -> 41488 | B6: =回测!F6 -> 100425.95 | C6: =回测!K6 -> 否 | D6: =COUNTIF($C$2:C6,"是") -> 1 | E6: =IF(COUNTA(F$2:F6)<2,0,AVERAGE(F$2:F6)/_xlfn.STDEV.P(F$2:F6)*SQRT(252)) -> 3.5463432 | F6: =IF(B5=0,0,B6/B5-1) -> -0.0069815059 | G6: =MAX($B$2:$B6) -> 101132 | H6: =1-($B6/$G6) -> 0.0069815059 | I6: =MAX($I5,$H6) -> 0.0069815059
A7: =回测!A7 -> 41489 | B7: =回测!F7 -> 100425.95 | C7: =回测!K7 -> 否 | D7: =COUNTIF($C$2:C7,"是") -> 1 | E7: =IF(COUNTA(F$2:F7)<2,0,AVERAGE(F$2:F7)/_xlfn.STDEV.P(F$2:F7)*SQRT(252)) -> 3.1562331 | F7: =IF(B6=0,0,B7/B6-1) -> 0 | G7: =MAX($B$2:$B7) -> 101132 | H7: =1-($B7/$G7) -> 0.0069815059 | I7: =MAX($I6,$H7) -> 0.0069815059
A8: =回测!A8 -> 41490 | B8: =回测!F8 -> 100425.95 | C8: =回测!K8 -> 否 | D8: =COUNTIF($C$2:C8,"是") -> 1 | E8: =IF(COUNTA(F$2:F8)<2,0,AVERAGE(F$2:F8)/_xlfn.STDEV.P(F$2:F8)*SQRT(252)) -> 2.8717886 | F8: =IF(B7=0,0,B8/B7-1) -> 0 | G8: =MAX($B$2:$B8) -> 101132 | H8: =1-($B8/$G8) -> 0.0069815059 | I8: =MAX($I7,$H8) -> 0.0069815059
A9: =回测!A9 -> 41491 | B9: =回测!F9 -> 101285.45 | C9: =回测!K9 -> 否 | D9: =COUNTIF($C$2:C9,"是") -> 1 | E9: =IF(COUNTA(F$2:F9)<2,0,AVERAGE(F$2:F9)/_xlfn.STDEV.P(F$2:F9)*SQRT(252)) -> 6.3664631 | F9: =IF(B8=0,0,B9/B8-1) -> 0.0085585865 | G9: =MAX($B$2:$B9) -> 101285.45 | H9: =1-($B9/$G9) -> 0 | I9: =MAX($I8,$H9) -> 0.0069815059
A10: =回测!A10 -> 41492 | B10: =回测!F10 -> 101082.78 | C10: =回测!K10 -> 否 | D10: =COUNTIF($C$2:C10,"是") -> 1 | E10: =IF(COUNTA(F$2:F10)<2,0,AVERAGE(F$2:F10)/_xlfn.STDEV.P(F$2:F10)*SQRT(252)) -> 4.8213494 | F10: =IF(B9=0,0,B10/B9-1) -> -0.0020009874 | G10: =MAX($B$2:$B10) -> 101285.45 | H10: =1-($B10/$G10) -> 0.0020009874 | I10: =MAX($I9,$H10) -> 0.0069815059
A11: =回测!A11 -> 41493 | B11: =回测!F11 -> 100653.54 | C11: =回测!K11 -> 否 | D11: =COUNTIF($C$2:C11,"是") -> 1 | E11: =IF(COUNTA(F$2:F11)<2,0,AVERAGE(F$2:F11)/_xlfn.STDEV.P(F$2:F11)*SQRT(252)) -> 2.553532 | F11: =IF(B10=0,0,B11/B10-1) -> -0.0042464274 | G11: =MAX($B$2:$B11) -> 101285.45 | H11: =1-($B11/$G11) -> 0.0062389177 | I11: =MAX($I10,$H11) -> 0.0069815059
A12: =回测!A12 -> 41494 | B12: =回测!F12 -> 100739.43 | C12: =回测!K12 -> 否 | D12: =COUNTIF($C$2:C12,"是") -> 1 | E12: =IF(COUNTA(F$2:F12)<2,0,AVERAGE(F$2:F12)/_xlfn.STDEV.P(F$2:F12)*SQRT(252)) -> 2.7351095 | F12: =IF(B11=0,0,B12/B11-1) -> 0.00085328609 | G12: =MAX($B$2:$B12) -> 101285.45 | H12: =1-($B12/$G12) -> 0.0053909552 | I12: =MAX($I11,$H12) -> 0.0069815059
A13: =回测!A13 -> 41495 | B13: =回测!F13 -> 101133.78 | C13: =回测!K13 -> 否 | D13: =COUNTIF($C$2:C13,"是") -> 1 | E13: =IF(COUNTA(F$2:F13)<2,0,AVERAGE(F$2:F13)/_xlfn.STDEV.P(F$2:F13)*SQRT(252)) -> 3.8823305 | F13: =IF(B12=0,0,B13/B12-1) -> 0.0039145538 | G13: =MAX($B$2:$B13) -> 101285.45 | H13: =1-($B13/$G13) -> 0.0014975047 | I13: =MAX($I12,$H13) -> 0.0069815059
A14: =回测!A14 -> 41496 | B14: =回测!F14 -> 101133.78 | C14: =回测!K14 -> 否 | D14: =COUNTIF($C$2:C14,"是") -> 1 | E14: =IF(COUNTA(F$2:F14)<2,0,AVERAGE(F$2:F14)/_xlfn.STDEV.P(F$2:F14)*SQRT(252)) -> 3.7078196 | F14: =IF(B13=0,0,B14/B13-1) -> 0 | G14: =MAX($B$2:$B14) -> 101285.45 | H14: =1-($B14/$G14) -> 0.0014975047 | I14: =MAX($I13,$H14) -> 0.0069815059
... A4518: =回测!A4518 -> 46000 | B4518: =回测!F4518 -> 195286.23 | C4518: =回测!K4518 -> 否 | D4518: =COUNTIF($C$2:C4518,"是") -> 58 | E4518: =IF(COUNTA(F$2:F4518)<2,0,AVERAGE(F$2:F4518)/_xlfn.STDEV.P(F$2:F4518)*SQRT(252)) -> 0.71772888 | F4518: =IF(B4517=0,0,B4518/B4517-1) -> -0.002864029 | G4518: =MAX($B$2:$B4518) -> 197524.9 | H4518: =1-($B4518/$G4518) -> 0.011333614 | I4518: =MAX($I4517,$H4518) -> 0.12754234

Sheet 参数调整
A1: 参数设置B3 | B1: 绘图J2
A2: 0.001 | B2: 22.909847
A3: 0.002 | B3: 28.170058
A4: 0.003 | B4: 33.829509
A5: 0.004 | B5: 23.952433
A6: 0.005 | B6: 22.137469
A7: 0.006 | B7: 22.082521
A8: 0.007 | B8: 16.972871
A9: 0.008 | B9: 17.680496
A10: 0.009 | B10: 15.297881
A11: 0.01 | B11: 16.97807
A12: 0.011 | B12: 21.381641
A13: 0.012 | B13: 14.767769
... A251: 0.25 | B251: 26.733146
